{
  "generator-jhipster": {
    "applicationType": "monolith",
    "gitCompany": "",
    "baseName": "jhipsterSampleApplication",
    "packageName": "com.mycompany.myapp",
    "packageFolder": "com/mycompany/myapp",
    "serverPort": 8080,
    "serviceDiscoveryType": false,
    "authenticationType": "jwt",
    "uaaBaseName": "../uaa",
    "cacheProvider": "ehcache",
    "enableHibernateCache": true,
    "websocket": false,
    "databaseType": "sql",
    "devDatabaseType": "h2Disk",
    "prodDatabaseType": "mysql",
    "searchEngine": false,
    "enableSwaggerCodegen": false,
    "messageBroker": false,
    "buildTool": "maven",
    "useSass": true,
    "clientPackageManager": "npm",
    "testFrameworks": ["cucumber"],
    "enableTranslation": true,
    "nativeLanguage": "en",
    "languages": ["fr", "en"],
    "clientFramework": "angularX",
    "jhiPrefix": "jhi",
    "jhipsterVersion": "6.8.0",
    "jwtSecretKey": "ZWJiZDlkODk0OGM2MDhhMDlhYjRlY2Y2Yjg2NDRkOWM1ZDBjNDUwNGEyMzM4M2RjZjE3ZGFkMmE1NGMyOTM2ZTRjZTI5ODJhOTlmMGM5NjNmNTQ0YmYwNjM1ZWI4ZDViMDFiNjBjMGUxMDc1ZjA5ODk5ZWRjNDI0YjBmNGFiOTU=",
    "embeddableLaunchScript": false,
    "clientTheme": "none",
    "creationTimestamp": 1586939965043,
    "entitySuffix": "",
    "dtoSuffix": "DTO",
    "otherModules": [],
    "blueprints": []
  },
  "git-provider": "GitHub",
  "git-company": "tarekEng",
  "repository-name": "jhipster-sample-application"
}
